opens3/__init__.py
opens3/client.py
opens3/exceptions.py
opens3/session.py
opens3/utils/__init__.py
opens3/utils/auth.py
opens3_sdk-0.1.7.dist-info/METADATA
opens3_sdk-0.1.7.dist-info/WHEEL
opens3_sdk-0.1.7.dist-info/top_level.txt
opens3_sdk-0.1.7.dist-info/RECORD
