Metadata-Version: 2.4
Name: openS3-sdk
Version: 0.1.7
Summary: A boto3-like SDK for OpenS3
Home-page: https://github.com/SourceBox-LLC/OpenS3-SDK
Author: SourceBox LLC
Author-email: info@sourcebox.com
Classifier: Programming Language :: Python :: 3
Classifier: License :: OSI Approved :: MIT License
Classifier: Operating System :: OS Independent
Requires-Python: >=3.6
Requires-Dist: requests>=2.25.0
Dynamic: author
Dynamic: author-email
Dynamic: classifier
Dynamic: description
Dynamic: description-content-type
Dynamic: home-page
Dynamic: requires-dist
Dynamic: requires-python
Dynamic: summary
